{
  "entrypoints": [
    "main"
  ],
  "origins": {
    "772": [
      2634,
      772
    ],
    "1538": [
      1869,
      3249,
      3347,
      4813,
      6061,
      7643,
      8401,
      1538
    ],
    "2237": [
      2237
    ],
    "3347": [
      1538,
      1869,
      3249,
      4212,
      4813,
      7643,
      3347
    ],
    "17896441": [
      1538,
      1869,
      8401
    ],
    "main": [
      1869,
      5354,
      8792
    ],
    "runtime~main": [
      1869,
      8792,
      5354
    ],
    "01a85c17": [
      1869,
      8209
    ],
    "0374b440": [
      6471
    ],
    "07a11b1f": [
      6306
    ],
    "0cb2590e": [
      4139
    ],
    "19017b1e": [
      6653
    ],
    "1b6ff2c5": [
      5754
    ],
    "1f391b9e": [
      1538,
      1869,
      6061
    ],
    "20777f46": [
      9618
    ],
    "219f6268": [
      4779
    ],
    "36994c47": [
      9858
    ],
    "3720c009": [
      1869,
      4787
    ],
    "3d50e1d3": [
      632
    ],
    "41ee9ed2": [
      2740
    ],
    "4bda0195": [
      335
    ],
    "4ecf7564": [
      2399
    ],
    "544367a9": [
      492
    ],
    "57b98f6e": [
      6285
    ],
    "5a05130f": [
      1258
    ],
    "5e95c892": [
      9647
    ],
    "621db11d": [
      1869,
      3347,
      4212
    ],
    "628da43c": [
      1722
    ],
    "6875c492": [
      1538,
      1869,
      3347,
      4813
    ],
    "7278acee": [
      5707
    ],
    "772a0fff": [
      7704
    ],
    "7c37d9f2": [
      9222
    ],
    "8058ddac": [
      1504
    ],
    "814f3328": [
      7472
    ],
    "82b384d2": [
      9766
    ],
    "8b8145cc": [
      8631
    ],
    "8f30deb2": [
      9137
    ],
    "90ed7b72": [
      3747
    ],
    "91cab89b": [
      6094
    ],
    "927eef92": [
      9190
    ],
    "9c00ad05": [
      5133
    ],
    "9e4087bc": [
      2711
    ],
    "a6aa9e1f": [
      1538,
      1869,
      3347,
      7643
    ],
    "a7456010": [
      1235
    ],
    "a7bd4aaa": [
      7098
    ],
    "a94703ab": [
      1869,
      9048
    ],
    "aba21aa0": [
      5742
    ],
    "acecf23e": [
      1903
    ],
    "b46cbca0": [
      2246
    ],
    "b6b33f4a": [
      9820
    ],
    "c4f5d8e4": [
      772,
      2634
    ],
    "c66d3daa": [
      9553
    ],
    "ccc49370": [
      1538,
      1869,
      3347,
      3249
    ],
    "df203c0f": [
      1869,
      4279
    ],
    "df377a91": [
      385
    ],
    "e678ec87": [
      7604
    ],
    "e685858b": [
      3140
    ],
    "f4d86323": [
      249
    ],
    "styles": [
      1538,
      3249,
      3347,
      4212,
      4279,
      4787,
      4813,
      5354,
      6061,
      7643,
      8209,
      8401,
      8792,
      9048,
      1869
    ]
  },
  "assets": {
    "249": {
      "js": [
        {
          "file": "assets/js/f4d86323.0b559664.js",
          "hash": "bcc1648d9fb87706",
          "publicPath": "/assets/js/f4d86323.0b559664.js"
        }
      ]
    },
    "335": {
      "js": [
        {
          "file": "assets/js/4bda0195.48a86f17.js",
          "hash": "b2eb9edb49188ac8",
          "publicPath": "/assets/js/4bda0195.48a86f17.js"
        }
      ]
    },
    "385": {
      "js": [
        {
          "file": "assets/js/df377a91.00fb36f8.js",
          "hash": "ea167b8d7c241da2",
          "publicPath": "/assets/js/df377a91.00fb36f8.js"
        }
      ]
    },
    "492": {
      "js": [
        {
          "file": "assets/js/544367a9.958c7dba.js",
          "hash": "ceaca792e6f436d3",
          "publicPath": "/assets/js/544367a9.958c7dba.js"
        }
      ]
    },
    "632": {
      "js": [
        {
          "file": "assets/js/3d50e1d3.40369506.js",
          "hash": "666c5a2f5786022e",
          "publicPath": "/assets/js/3d50e1d3.40369506.js"
        }
      ]
    },
    "772": {
      "js": [
        {
          "file": "assets/js/772.ba0fdd80.js",
          "hash": "3fc5e4c0932ac48a",
          "publicPath": "/assets/js/772.ba0fdd80.js"
        }
      ]
    },
    "1235": {
      "js": [
        {
          "file": "assets/js/a7456010.d7714613.js",
          "hash": "5ee34c5342ae84b9",
          "publicPath": "/assets/js/a7456010.d7714613.js"
        }
      ]
    },
    "1258": {
      "js": [
        {
          "file": "assets/js/5a05130f.02e3e7ab.js",
          "hash": "749f00fa73596622",
          "publicPath": "/assets/js/5a05130f.02e3e7ab.js"
        }
      ]
    },
    "1504": {
      "js": [
        {
          "file": "assets/js/8058ddac.d03a58fa.js",
          "hash": "0e46b6fb471a00ed",
          "publicPath": "/assets/js/8058ddac.d03a58fa.js"
        }
      ]
    },
    "1538": {
      "js": [
        {
          "file": "assets/js/1538.6c9135d3.js",
          "hash": "7d64166bfa05e9be",
          "publicPath": "/assets/js/1538.6c9135d3.js"
        }
      ]
    },
    "1722": {
      "js": [
        {
          "file": "assets/js/628da43c.48ad0760.js",
          "hash": "b33994e8e46bdf6d",
          "publicPath": "/assets/js/628da43c.48ad0760.js"
        }
      ]
    },
    "1869": {
      "css": [
        {
          "file": "assets/css/styles.a67e75aa.css",
          "hash": "ac3a62ecbdfffbed",
          "publicPath": "/assets/css/styles.a67e75aa.css"
        }
      ]
    },
    "1903": {
      "js": [
        {
          "file": "assets/js/acecf23e.e4fa13c0.js",
          "hash": "d6f480aee4407e89",
          "publicPath": "/assets/js/acecf23e.e4fa13c0.js"
        }
      ]
    },
    "2237": {
      "js": [
        {
          "file": "assets/js/2237.0fce18b8.js",
          "hash": "2fbc82c19be2e36b",
          "publicPath": "/assets/js/2237.0fce18b8.js"
        }
      ]
    },
    "2246": {
      "js": [
        {
          "file": "assets/js/b46cbca0.d28941b7.js",
          "hash": "57e1cd6cdb918954",
          "publicPath": "/assets/js/b46cbca0.d28941b7.js"
        }
      ]
    },
    "2399": {
      "js": [
        {
          "file": "assets/js/4ecf7564.8ed30f98.js",
          "hash": "f6f3c5b135bcec9c",
          "publicPath": "/assets/js/4ecf7564.8ed30f98.js"
        }
      ]
    },
    "2634": {
      "js": [
        {
          "file": "assets/js/c4f5d8e4.694d537e.js",
          "hash": "32f1057ab4d4113a",
          "publicPath": "/assets/js/c4f5d8e4.694d537e.js"
        }
      ]
    },
    "2711": {
      "js": [
        {
          "file": "assets/js/9e4087bc.b8ac661d.js",
          "hash": "31a3ccc3be997cfe",
          "publicPath": "/assets/js/9e4087bc.b8ac661d.js"
        }
      ]
    },
    "2740": {
      "js": [
        {
          "file": "assets/js/41ee9ed2.aaa892df.js",
          "hash": "0d6044d165358fe3",
          "publicPath": "/assets/js/41ee9ed2.aaa892df.js"
        }
      ]
    },
    "3140": {
      "js": [
        {
          "file": "assets/js/e685858b.b821f98e.js",
          "hash": "e676d449dcf0ef17",
          "publicPath": "/assets/js/e685858b.b821f98e.js"
        }
      ]
    },
    "3249": {
      "js": [
        {
          "file": "assets/js/ccc49370.5fdab76e.js",
          "hash": "03648820903eaa2c",
          "publicPath": "/assets/js/ccc49370.5fdab76e.js"
        }
      ]
    },
    "3347": {
      "js": [
        {
          "file": "assets/js/3347.7806b886.js",
          "hash": "332b37f93a1abd3a",
          "publicPath": "/assets/js/3347.7806b886.js"
        }
      ]
    },
    "3747": {
      "js": [
        {
          "file": "assets/js/90ed7b72.df52c99b.js",
          "hash": "20ff30585595ae44",
          "publicPath": "/assets/js/90ed7b72.df52c99b.js"
        }
      ]
    },
    "4139": {
      "js": [
        {
          "file": "assets/js/0cb2590e.8098da8d.js",
          "hash": "54d61feaf30b2361",
          "publicPath": "/assets/js/0cb2590e.8098da8d.js"
        }
      ]
    },
    "4212": {
      "js": [
        {
          "file": "assets/js/621db11d.f4cb7780.js",
          "hash": "f1abcee9db749d64",
          "publicPath": "/assets/js/621db11d.f4cb7780.js"
        }
      ]
    },
    "4279": {
      "js": [
        {
          "file": "assets/js/df203c0f.e5c750c0.js",
          "hash": "3168f4d1c4829616",
          "publicPath": "/assets/js/df203c0f.e5c750c0.js"
        }
      ]
    },
    "4779": {
      "js": [
        {
          "file": "assets/js/219f6268.41e16d40.js",
          "hash": "4fe34e7ef0bf27fb",
          "publicPath": "/assets/js/219f6268.41e16d40.js"
        }
      ]
    },
    "4787": {
      "js": [
        {
          "file": "assets/js/3720c009.85231157.js",
          "hash": "430f217cd1e5251a",
          "publicPath": "/assets/js/3720c009.85231157.js"
        }
      ]
    },
    "4813": {
      "js": [
        {
          "file": "assets/js/6875c492.395efe52.js",
          "hash": "edd6ab228b4aacb5",
          "publicPath": "/assets/js/6875c492.395efe52.js"
        }
      ]
    },
    "5133": {
      "js": [
        {
          "file": "assets/js/9c00ad05.e3746722.js",
          "hash": "ee46418a21da675f",
          "publicPath": "/assets/js/9c00ad05.e3746722.js"
        }
      ]
    },
    "5354": {
      "js": [
        {
          "file": "assets/js/runtime~main.389cc41c.js",
          "hash": "122cbdea4d552af5",
          "publicPath": "/assets/js/runtime~main.389cc41c.js"
        }
      ]
    },
    "5707": {
      "js": [
        {
          "file": "assets/js/7278acee.399e5c90.js",
          "hash": "7f8ea71214a1d146",
          "publicPath": "/assets/js/7278acee.399e5c90.js"
        }
      ]
    },
    "5742": {
      "js": [
        {
          "file": "assets/js/aba21aa0.a78f3f57.js",
          "hash": "e70a47e70101ac41",
          "publicPath": "/assets/js/aba21aa0.a78f3f57.js"
        }
      ]
    },
    "5754": {
      "js": [
        {
          "file": "assets/js/1b6ff2c5.ab1596f5.js",
          "hash": "ac40d535bb267534",
          "publicPath": "/assets/js/1b6ff2c5.ab1596f5.js"
        }
      ]
    },
    "6061": {
      "js": [
        {
          "file": "assets/js/1f391b9e.c3573360.js",
          "hash": "5b76cfaf0a6cf00f",
          "publicPath": "/assets/js/1f391b9e.c3573360.js"
        }
      ]
    },
    "6094": {
      "js": [
        {
          "file": "assets/js/91cab89b.6102d347.js",
          "hash": "c13ddc67e82a052f",
          "publicPath": "/assets/js/91cab89b.6102d347.js"
        }
      ]
    },
    "6285": {
      "js": [
        {
          "file": "assets/js/57b98f6e.337fddf1.js",
          "hash": "18f7f8e3d9b32616",
          "publicPath": "/assets/js/57b98f6e.337fddf1.js"
        }
      ]
    },
    "6306": {
      "js": [
        {
          "file": "assets/js/07a11b1f.2d66c5d5.js",
          "hash": "e2f017fe98a140bb",
          "publicPath": "/assets/js/07a11b1f.2d66c5d5.js"
        }
      ]
    },
    "6471": {
      "js": [
        {
          "file": "assets/js/0374b440.4bfd7a3d.js",
          "hash": "39d0af2c1171bf62",
          "publicPath": "/assets/js/0374b440.4bfd7a3d.js"
        }
      ]
    },
    "6653": {
      "js": [
        {
          "file": "assets/js/19017b1e.5516f3e5.js",
          "hash": "0cced5a38810952a",
          "publicPath": "/assets/js/19017b1e.5516f3e5.js"
        }
      ]
    },
    "7098": {
      "js": [
        {
          "file": "assets/js/a7bd4aaa.752e05a5.js",
          "hash": "d849a1104da8eddd",
          "publicPath": "/assets/js/a7bd4aaa.752e05a5.js"
        }
      ]
    },
    "7472": {
      "js": [
        {
          "file": "assets/js/814f3328.28fb1cbd.js",
          "hash": "153afc8a12c092c4",
          "publicPath": "/assets/js/814f3328.28fb1cbd.js"
        }
      ]
    },
    "7604": {
      "js": [
        {
          "file": "assets/js/e678ec87.d342ee74.js",
          "hash": "f2434c684606fa57",
          "publicPath": "/assets/js/e678ec87.d342ee74.js"
        }
      ]
    },
    "7643": {
      "js": [
        {
          "file": "assets/js/a6aa9e1f.9173b9bc.js",
          "hash": "e8e46a906b64911f",
          "publicPath": "/assets/js/a6aa9e1f.9173b9bc.js"
        }
      ]
    },
    "7704": {
      "js": [
        {
          "file": "assets/js/772a0fff.32ba0ef8.js",
          "hash": "c21ac365136d555f",
          "publicPath": "/assets/js/772a0fff.32ba0ef8.js"
        }
      ]
    },
    "8209": {
      "js": [
        {
          "file": "assets/js/01a85c17.aa0c59db.js",
          "hash": "a3362ec2596fa41d",
          "publicPath": "/assets/js/01a85c17.aa0c59db.js"
        }
      ]
    },
    "8401": {
      "js": [
        {
          "file": "assets/js/17896441.03109357.js",
          "hash": "43dc9311b655e1de",
          "publicPath": "/assets/js/17896441.03109357.js"
        }
      ]
    },
    "8631": {
      "js": [
        {
          "file": "assets/js/8b8145cc.f701a858.js",
          "hash": "1ffed764afedb579",
          "publicPath": "/assets/js/8b8145cc.f701a858.js"
        }
      ]
    },
    "8792": {
      "js": [
        {
          "file": "assets/js/main.ed17b324.js",
          "hash": "b43de1adbebe14cd",
          "publicPath": "/assets/js/main.ed17b324.js"
        }
      ]
    },
    "9048": {
      "js": [
        {
          "file": "assets/js/a94703ab.08775427.js",
          "hash": "5492c5409b330716",
          "publicPath": "/assets/js/a94703ab.08775427.js"
        }
      ]
    },
    "9137": {
      "js": [
        {
          "file": "assets/js/8f30deb2.75e55a42.js",
          "hash": "2c5ef80b2d0cea2a",
          "publicPath": "/assets/js/8f30deb2.75e55a42.js"
        }
      ]
    },
    "9190": {
      "js": [
        {
          "file": "assets/js/927eef92.d37c5b76.js",
          "hash": "2776d496d7115211",
          "publicPath": "/assets/js/927eef92.d37c5b76.js"
        }
      ]
    },
    "9222": {
      "js": [
        {
          "file": "assets/js/7c37d9f2.e2c6517f.js",
          "hash": "73c816a3b5e1ec77",
          "publicPath": "/assets/js/7c37d9f2.e2c6517f.js"
        }
      ]
    },
    "9553": {
      "js": [
        {
          "file": "assets/js/c66d3daa.e693d6ce.js",
          "hash": "08a45fdf98c0cb97",
          "publicPath": "/assets/js/c66d3daa.e693d6ce.js"
        }
      ]
    },
    "9618": {
      "js": [
        {
          "file": "assets/js/20777f46.3120d6b9.js",
          "hash": "becc822366b2e5b8",
          "publicPath": "/assets/js/20777f46.3120d6b9.js"
        }
      ]
    },
    "9647": {
      "js": [
        {
          "file": "assets/js/5e95c892.920695bf.js",
          "hash": "b6d50c4c5f8b23f2",
          "publicPath": "/assets/js/5e95c892.920695bf.js"
        }
      ]
    },
    "9766": {
      "js": [
        {
          "file": "assets/js/82b384d2.2eaa6977.js",
          "hash": "ba7170db677ab4be",
          "publicPath": "/assets/js/82b384d2.2eaa6977.js"
        }
      ]
    },
    "9820": {
      "js": [
        {
          "file": "assets/js/b6b33f4a.318e53db.js",
          "hash": "cd5d44339b8436d0",
          "publicPath": "/assets/js/b6b33f4a.318e53db.js"
        }
      ]
    },
    "9858": {
      "js": [
        {
          "file": "assets/js/36994c47.3a56cc9d.js",
          "hash": "140593465c82d1dd",
          "publicPath": "/assets/js/36994c47.3a56cc9d.js"
        }
      ]
    }
  }
}